examples/__init__.py
examples/fastapi_demo.py
pyzolocal/__init__.py
pyzolocal/apis/__init__.py
pyzolocal/apis/base.py
pyzolocal/apis/fastapi.py
pyzolocal/apis/flask.py
pyzolocal/beans/__init__.py
pyzolocal/beans/enum.py
pyzolocal/beans/struct.py
pyzolocal/beans/types.py
pyzolocal/files/__init__.py
pyzolocal/files/base.py
pyzolocal/files/gets.py
pyzolocal/gui/__init__.py
pyzolocal/prefs/__init__.py
pyzolocal/prefs/base.py
pyzolocal/prefs/common.py
pyzolocal/prefs/gets.py
pyzolocal/sqls/__init__.py
pyzolocal/sqls/base.py
pyzolocal/sqls/gets.py
pyzolocal/sync/__init__.py
pyzolocal/sync/base.py
pyzolocal/sync/bypy.py
pyzolocal/sync/ftp.py
pyzolocal/sync/gists.py
zolocal-0.2.0.dist-info/LICENSE
zolocal-0.2.0.dist-info/METADATA
zolocal-0.2.0.dist-info/WHEEL
zolocal-0.2.0.dist-info/entry_points.txt
zolocal-0.2.0.dist-info/top_level.txt
zolocal-0.2.0.dist-info/RECORD
